procastro/__init__.py
procastro/astro/__init__.py
procastro/astro/astro.py
procastro/astro/coordinates.py
procastro/astro/exoplanet.py
procastro/astro/ifu.py
procastro/astro/images/bennu_osiris_rex_ocams_global_albedo_mosaic_6_25cm.xml
procastro/astro/images/bennu_osiris_rex_ocams_global_pan_mosaic_5cm.xml
procastro/astro/images/callisto_galileo_voyager_global_mercator_mosaic.xml
procastro/astro/images/callisto_galileo_voyager_global_mosaic_1km.xml
procastro/astro/images/callisto_galileo_voyager_simple_cylindrical_global_map (1).xml
procastro/astro/images/callisto_galileo_voyager_simple_cylindrical_global_map.xml
procastro/astro/images/ceres_dawn_fc2_hamo_global_dtm_137m.xml
procastro/astro/images/ceres_dawn_fc_global_mosaic_400m.xml
procastro/astro/images/ceres_dawn_fc_hamo_colorized_shaded_relief_60ppd_137mp_oct_2016.xml
procastro/astro/images/ceres_dawn_fc_hamo_hillshade_60ppd_137mp_oct_2016.xml
procastro/astro/images/dione_cassini_voyager_global_mosaic_154m.xml
procastro/astro/images/enceladus-cassini-global-mosaic-100m-schenk.xml
procastro/astro/images/enceladus_cassini_global_mosaic_110m.xml
procastro/astro/images/europa_control_network.xml
procastro/astro/images/europa_voyager_galileo_ssi_global_mosaic_500m.xml
procastro/astro/images/ganymede_voyager_galileo_ssi_color_global_mosaic_1_4km.xml
procastro/astro/images/ganymede_voyager_galileo_ssi_global_mosaic_1km.xml
procastro/astro/images/global_geologic_map_of_ganymede_sim3237.xml
procastro/astro/images/iapetus_cassini_voyager_global_mosaic_803m.xml
procastro/astro/images/iapetus_voyager_airbrush_global_mosaic_783m.xml
procastro/astro/images/io_galileo_ssi_global_color_merge_mosaic_1km (1).xml
procastro/astro/images/io_galileo_ssi_global_color_merge_mosaic_1km.xml
procastro/astro/images/io_galileo_ssi_voyager_color_merged_global_mosaic_1km.xml
procastro/astro/images/io_voyager_image_control_network.xml
procastro/astro/images/mars_human_exploration_zone_dem_archive_2023.xml
procastro-0.2.2.dist-info/LICENSE
procastro-0.2.2.dist-info/METADATA
procastro-0.2.2.dist-info/WHEEL
procastro-0.2.2.dist-info/RECORD
